mini_toker/__init__.py
mini_toker/tokenizer.py
mini_toker/tokens.py
mini_toker-0.4.0.dist-info/METADATA
mini_toker-0.4.0.dist-info/WHEEL
mini_toker-0.4.0.dist-info/top_level.txt
mini_toker-0.4.0.dist-info/RECORD
